LICENSE
README.md
pyproject.toml
ragbear/__init__.py
ragbear.egg-info/PKG-INFO
ragbear.egg-info/SOURCES.txt
ragbear.egg-info/dependency_links.txt
ragbear.egg-info/requires.txt
ragbear.egg-info/top_level.txt