Metadata-Version: 2.1
Name: ragbear
Version: 0.0.1a1
Summary: Comprehensive RAG implementations
Author-email: Oyster Oil <infinitesheldon@gmail.com>
License: MIT License
Project-URL: repository, https://github.com/oysteroil/ragbear
Classifier: Development Status :: 4 - Beta
Classifier: Intended Audience :: Developers
Classifier: License :: OSI Approved :: MIT License
Classifier: Programming Language :: Python :: 3
Classifier: Programming Language :: Python :: 3.8
Classifier: Programming Language :: Python :: 3.9
Classifier: Programming Language :: Python :: 3.10
Classifier: Programming Language :: Python :: 3.11
Classifier: Programming Language :: Python :: 3.12
Requires-Python: >=3.8
License-File: LICENSE
Provides-Extra: dev
Provides-Extra: build
Provides-Extra: test
Requires-Dist: pytest<9.0,>=8.1.1; extra == "test"
